pyeasydraw/__init__.py
pyeasydraw-0.0.5.dist-info/METADATA
pyeasydraw-0.0.5.dist-info/WHEEL
pyeasydraw-0.0.5.dist-info/top_level.txt
pyeasydraw-0.0.5.dist-info/RECORD
