Metadata-Version: 2.1
Name: pyeasydraw
Version: 0.0.5
Summary: Python进行画画。
Home-page: https://github.com/Gry/pyeasydraw
Author: 郭若垚
Author-email: yao1127@aliyun.com
License: GPLv3
Platform: UNKNOWN
Classifier: Programming Language :: Python :: 3
Classifier: License :: OSI Approved :: GNU General Public License v3 (GPLv3)
Classifier: Operating System :: OS Independent
Requires-Python: >=2.8
